masumi/__init__.py
masumi/config.py
masumi/helper_functions.py
masumi/payment.py
masumi/purchase.py
masumi/registry.py
masumi-0.1.41.dist-info/licenses/LICENSE
masumi-0.1.41.dist-info/METADATA
masumi-0.1.41.dist-info/WHEEL
masumi-0.1.41.dist-info/top_level.txt
masumi-0.1.41.dist-info/RECORD
