Metadata-Version: 2.4
Name: masumi
Version: 0.1.41
Summary: Masumi Payment Module for Cardano blockchain integration
Home-page: https://github.com/masumi-network/masumi
Author: Patrick Tobler
Author-email: patrick@nmkr.io
Classifier: Programming Language :: Python :: 3
Classifier: License :: OSI Approved :: MIT License
Classifier: Operating System :: OS Independent
Requires-Python: >=3.8
License-File: LICENSE
Requires-Dist: aiohttp>=3.8.0
Requires-Dist: pytest>=7.0.0
Requires-Dist: pytest-asyncio>=0.18.0
Requires-Dist: canonicaljson>=1.6.3
Dynamic: author
Dynamic: author-email
Dynamic: classifier
Dynamic: description
Dynamic: description-content-type
Dynamic: home-page
Dynamic: license-file
Dynamic: requires-dist
Dynamic: requires-python
Dynamic: summary
